DiadFit/CO2_EOS.py
DiadFit/CO2_in_bubble_error.py
DiadFit/H2O_fitting.py
DiadFit/Highrho_polyfit_data.pkl
DiadFit/Highrho_polyfit_dataUCB_1117_1400.pkl
DiadFit/Highrho_polyfit_dataUCB_1117_1447.pkl
DiadFit/Highrho_polyfit_dataUCB_1220_1400.pkl
DiadFit/Highrho_polyfit_dataUCB_1220_1447.pkl
DiadFit/Highrho_polyfit_dataUCB_1220_1567.pkl
DiadFit/Highrho_polyfit_data_CCMR.pkl
DiadFit/Highrho_polyfit_data_CMASS.pkl
DiadFit/Highrho_polyfit_data_CMASS_24C.pkl
DiadFit/Lowrho_polyfit_data.pkl
DiadFit/Lowrho_polyfit_dataUCB_1117_1400.pkl
DiadFit/Lowrho_polyfit_dataUCB_1117_1447.pkl
DiadFit/Lowrho_polyfit_dataUCB_1220_1400.pkl
DiadFit/Lowrho_polyfit_dataUCB_1220_1447.pkl
DiadFit/Lowrho_polyfit_dataUCB_1220_1567.pkl
DiadFit/Lowrho_polyfit_data_CCMR.pkl
DiadFit/Lowrho_polyfit_data_CMASS.pkl
DiadFit/Lowrho_polyfit_data_CMASS_24C.pkl
DiadFit/Mediumrho_polyfit_data.pkl
DiadFit/Mediumrho_polyfit_dataUCB_1117_1400.pkl
DiadFit/Mediumrho_polyfit_dataUCB_1117_1447.pkl
DiadFit/Mediumrho_polyfit_dataUCB_1220_1400.pkl
DiadFit/Mediumrho_polyfit_dataUCB_1220_1447.pkl
DiadFit/Mediumrho_polyfit_dataUCB_1220_1567.pkl
DiadFit/Mediumrho_polyfit_data_CCMR.pkl
DiadFit/Mediumrho_polyfit_data_CMASS.pkl
DiadFit/Psensor.py
DiadFit/__init__.py
DiadFit/_version.py
DiadFit/argon_lines.py
DiadFit/cosmicray_filter.py
DiadFit/densimeter_fitting.py
DiadFit/densimeters.py
DiadFit/density_depth_crustal_profiles.py
DiadFit/diads.py
DiadFit/error_propagation.py
DiadFit/importing_data_files.py
DiadFit/lookup_table.csv
DiadFit/lookup_table_noneg.csv
DiadFit/molar_gas_proportions.py
DiadFit/ne_lines.py
DiadFit/relaxfi_PW.py
DiadFit/relaxifi.py
DiadFit/smoothed_polyfit_June25_UCB.pkl
DiadFit-1.0.12.dist-info/LICENSE.txt
DiadFit-1.0.12.dist-info/METADATA
DiadFit-1.0.12.dist-info/WHEEL
DiadFit-1.0.12.dist-info/top_level.txt
DiadFit-1.0.12.dist-info/RECORD
