Metadata-Version: 2.1
Name: DiadFit
Version: 1.0.12
Summary: DiadFit
Home-page: https://github.com/PennyWieser/DiadFit
Author: Penny Wieser
Author-email: penny.wieser@gmail.com
License: UNKNOWN
Platform: UNKNOWN
Classifier: Programming Language :: Python :: 3
Classifier: Operating System :: OS Independent
Requires-Python: >=3.8
Requires-Dist: pandas
Requires-Dist: numpy<2
Requires-Dist: matplotlib
Requires-Dist: scikit-learn
Requires-Dist: scipy>1.6
Requires-Dist: lmfit>=1.1.0
Requires-Dist: tqdm
Requires-Dist: python-docx
